{
  "thumb": "poster.png",
  "enter": "00_0",
  "sources": "http://brechtapp.eu/apsurdism",
  "audio": "audio",
  "image": "image",
  "events": [],
  "sizes": [
    "720",
    "360"
  ],
  "scenes": {
    "00_0": {
      "name": "00_0",
      "onend": "00_1",
      "vsrc": "00_0.mp4",
      "poster": {
        "image": "http://brechtapp.eu/apsurdism/image/poster.png"
      }
    },
    "00_1": {
      "name": "00_1",
      "onend": "00_2",
      "vsrc": "00_1.mp4"
    },
    "00_2": {
      "name": "00_2",
      "vsrc": "00_2.mp4",
      "events": [
        {
          "type": "click",
          "scene": "00_2_1",
          "constraints": {
            "timespan": [
              8
            ],
            "hitbox": [
              6.38,
              54.47,
              18.6,
              45.12
            ]
          }
        },
        {
          "type": "click",
          "scene": "00_2_2",
          "constraints": {
            "timespan": [
              8
            ],
            "hitbox": [
              22.51,
              58.6,
              34.86,
              40.03
            ]
          }
        },
        {
          "type": "click",
          "scene": "00_2_3",
          "constraints": {
            "timespan": [
              8
            ],
            "hitbox": [
              39.51,
              62.17,
              51.73,
              36.87
            ]
          }
        },
        {
          "type": "click",
          "scene": "00_2_4",
          "constraints": {
            "timespan": [
              8
            ],
            "hitbox": [
              57.11,
              76.47,
              69.21,
              27.24
            ]
          }
        },
        {
          "type": "click",
          "scene": "00_2_5",
          "constraints": {
            "timespan": [
              8
            ],
            "hitbox": [
              76.55,
              73.93,
              88.53,
              28.13
            ]
          }
        }
      ]
    },
    "00_2_1": {
      "name": "00_2_1",
      "onend": "00_3",
      "vsrc": "00_2_1.mp4"
    },
    "00_2_2": {
      "name": "00_2_2",
      "onend": "00_3",
      "vsrc": "00_2_2.mp4"
    },
    "00_2_3": {
      "name": "00_2_3",
      "onend": "00_3",
      "vsrc": "00_2_3.mp4"
    },
    "00_2_4": {
      "name": "00_2_4",
      "onend": "00_3",
      "vsrc": "00_2_4.mp4"
    },
    "00_2_5": {
      "name": "00_2_5",
      "onend": "00_3",
      "vsrc": "00_2_5.mp4"
    },
    "00_3": {
      "name": "00_3",
      "onend": "00_4",
      "vsrc": "00_3.mp4"
    },
    "00_4": {
      "name": "00_4",
      "vsrc": "00_4.mp4",
      "events": [
        {
          "type": "click",
          "scene": "00_4_1",
          "constraints": {
            "timespan": [
              10
            ],
            "hitbox": [
              27.89,
              79.57,
              39.87,
              22.36
            ]
          }
        },
        {
          "type": "click",
          "scene": "00_4_2",
          "constraints": {
            "timespan": [
              10
            ],
            "hitbox": [
              41.71,
              84.38,
              53.93,
              18.09
            ]
          }
        },
        {
          "type": "click",
          "scene": "00_4_3",
          "constraints": {
            "timespan": [
              10
            ],
            "hitbox": [
              56.38,
              80.33,
              67.99,
              22.91
            ]
          }
        },
        {
          "type": "click",
          "scene": "00_4_4",
          "constraints": {
            "timespan": [
              10
            ],
            "hitbox": [
              70.19,
              81.91,
              81.32,
              20.29
            ]
          }
        },
        {
          "type": "click",
          "scene": "00_4_5",
          "constraints": {
            "timespan": [
              10
            ],
            "hitbox": [
              83.64,
              73.66,
              95.25,
              25.86
            ]
          }
        }
      ]
    },
    "00_4_1": {
      "name": "00_4_1",
      "onend": "00_5",
      "vsrc": "00_4_1.mp4"
    },
    "00_4_2": {
      "name": "00_4_2",
      "onend": "00_5",
      "vsrc": "00_4_2.mp4"
    },
    "00_4_3": {
      "name": "00_4_3",
      "onend": "00_5",
      "vsrc": "00_4_3.mp4"
    },
    "00_4_4": {
      "name": "00_4_4",
      "onend": "00_5",
      "vsrc": "00_4_4.mp4"
    },
    "00_4_5": {
      "name": "00_4_5",
      "onend": "00_5",
      "vsrc": "00_4_5.mp4"
    },
    "00_5": {
      "name": "00_5",
      "onend": "00_6",
      "vsrc": "00_5.mp4"
    },
    "00_6": {
      "name": "00_6",
      "onend": "01",
      "vsrc": "00_6.mp4"
    },
    "01": {
      "name": "01",
      "vsrc": "01.mp4",
      "events": [
        {
          "type": "click",
          "scene": "01_1",
          "constraints": {
            "timespan": [
              21
            ],
            "hitbox": [
              9.19,
              49.66,
              19.7,
              15.55
            ]
          }
        },
        {
          "type": "click",
          "scene": "01_2",
          "constraints": {
            "timespan": [
              21
            ],
            "hitbox": [
              9.19,
              49.66,
              19.7,
              15.55
            ]
          }
        },
        {
          "type": "click",
          "scene": "01_3",
          "constraints": {
            "timespan": [
              21
            ],
            "hitbox": [
              31.56,
              49.59,
              40.85,
              16.37
            ]
          }
        },
        {
          "type": "click",
          "scene": "01_4",
          "constraints": {
            "timespan": [
              21
            ],
            "hitbox": [
              10.29,
              83.9,
              20.93,
              50.89
            ]
          }
        },
        {
          "type": "click",
          "scene": "01_5",
          "constraints": {
            "timespan": [
              21
            ],
            "hitbox": [
              21.78,
              83.69,
              30.95,
              50.28
            ]
          }
        },
        {
          "type": "click",
          "scene": "01_6",
          "constraints": {
            "timespan": [
              21
            ],
            "hitbox": [
              32.17,
              83.83,
              41.71,
              50.14
            ]
          }
        },
        {
          "type": "click",
          "scene": "01_7",
          "constraints": {
            "timespan": [
              21
            ],
            "hitbox": [
              42.93,
              83.49,
              51.73,
              16.1
            ]
          }
        },
        {
          "type": "click",
          "scene": "01_8",
          "constraints": {
            "timespan": [
              21
            ],
            "hitbox": [
              53.2,
              82.59,
              63.47,
              17.41
            ]
          }
        },
        {
          "type": "timeout",
          "span": 25000,
          "scene_span": [
            "01"
          ],
          "sound": {
            "src": [
              "delay/clip_01.mp3",
              "delay/clip_02.mp3",
              "delay/clip_03.mp3",
              "delay/clip_04.mp3",
              "delay/clip_05.mp3",
              "delay/clip_06.mp3",
              "delay/clip_07.mp3",
              "delay/clip_08.mp3",
              "delay/clip_09.mp3",
              "delay/clip_10.mp3",
              "delay/clip_11.mp3",
              "delay/clip_12.mp3",
              "delay/clip_13.mp3",
              "delay/clip_14.mp3",
              "delay/clip_15.mp3"
            ],
            "onend": {
              "type": "repeat",
              "unbound": true,
              "timeout": 4000
            }
          }
        },
        {
          "type": "timeout",
          "span": 11000,
          "single": true,
          "sound": {
            "src": "bg/01.mp3",
            "loop": true,
            "volume": 0.5
          },
          "scene_span": [
            "01",
            "01_1",
            "01_2",
            "01_3",
            "01_4",
            "01_5",
            "01_6",
            "01_7",
            "01_8"
          ]
        }
      ]
    },
    "01_1": {
      "name": "01_1",
      "onend": "01_n",
      "vsrc": "01_1.mp4"
    },
    "01_2": {
      "name": "01_2",
      "onend": "01_n",
      "vsrc": "01_2.mp4"
    },
    "01_3": {
      "name": "01_3",
      "onend": "01_n",
      "vsrc": "01_3.mp4"
    },
    "01_4": {
      "name": "01_4",
      "onend": "01_n",
      "vsrc": "01_4.mp4"
    },
    "01_5": {
      "name": "01_5",
      "onend": "01_n",
      "vsrc": "01_5.mp4"
    },
    "01_6": {
      "name": "01_6",
      "onend": "01_n",
      "vsrc": "01_6.mp4"
    },
    "01_7": {
      "name": "01_7",
      "onend": "01_n",
      "vsrc": "01_7.mp4"
    },
    "01_8": {
      "name": "01_8",
      "onend": {
        "scene": "01",
        "time": 22.3
      },
      "vsrc": "01_8.mp4"
    },
    "01_n": {
      "name": "01_n",
      "vsrc": "01_n.mp4",
      "events": [
        {
          "type": "click",
          "scene": "02",
          "constraints": {
            "timespan": [
              1.9
            ]
          }
        }
      ]
    },
    "02": {
      "name": "02",
      "vsrc": "02.mp4",
      "events": [
        {
          "type": "click",
          "scene": "02_1",
          "constraints": {
            "timespan": [
              16
            ],
            "hitbox": [
              9.31,
              47.66,
              19.95,
              13.42
            ]
          }
        },
        {
          "type": "click",
          "scene": "02_2",
          "constraints": {
            "timespan": [
              16
            ],
            "hitbox": [
              20.68,
              47.8,
              31.07,
              13.62
            ]
          }
        },
        {
          "type": "click",
          "scene": "02_3",
          "constraints": {
            "timespan": [
              16
            ],
            "hitbox": [
              32.42,
              47.8,
              42.07,
              14.45
            ]
          }
        },
        {
          "type": "click",
          "scene": "02_4",
          "constraints": {
            "timespan": [
              16
            ],
            "hitbox": [
              10.04,
              82.87,
              20.31,
              48.76
            ]
          }
        },
        {
          "type": "click",
          "scene": "02_5",
          "constraints": {
            "timespan": [
              16
            ],
            "hitbox": [
              21.29,
              82.39,
              31.32,
              48.69
            ]
          }
        },
        {
          "type": "click",
          "scene": "02_6",
          "constraints": {
            "timespan": [
              16
            ],
            "hitbox": [
              32.17,
              82.46,
              42.2,
              48.62
            ]
          }
        },
        {
          "type": "click",
          "scene": "02_7",
          "constraints": {
            "timespan": [
              16
            ],
            "hitbox": [
              44.03,
              81.98,
              53.69,
              14.72
            ]
          }
        },
        {
          "type": "click",
          "scene": "02_8",
          "constraints": {
            "timespan": [
              16
            ],
            "hitbox": [
              56.01,
              81.91,
              65.42,
              15.2
            ]
          }
        },
        {
          "type": "timeout",
          "span": 21000,
          "sound": {
            "src": [
              "delay/clip_01.mp3",
              "delay/clip_02.mp3",
              "delay/clip_03.mp3",
              "delay/clip_04.mp3",
              "delay/clip_05.mp3",
              "delay/clip_06.mp3",
              "delay/clip_07.mp3",
              "delay/clip_08.mp3",
              "delay/clip_09.mp3",
              "delay/clip_10.mp3",
              "delay/clip_11.mp3",
              "delay/clip_12.mp3",
              "delay/clip_13.mp3",
              "delay/clip_14.mp3",
              "delay/clip_15.mp3"
            ],
            "onend": {
              "type": "repeat",
              "unbound": true,
              "timeout": 4000
            }
          }
        },
        {
          "type": "timeout",
          "span": 5000,
          "single": true,
          "sound": {
            "src": "bg/02.mp3",
            "loop": true,
            "volume": 0.5
          },
          "scene_span": [
            "02",
            "02_1",
            "02_2",
            "02_3",
            "02_4",
            "02_5",
            "02_6",
            "02_7",
            "02_8"
          ]
        }
      ]
    },
    "02_1": {
      "name": "02_1",
      "onend": "02_n",
      "vsrc": "02_1.mp4"
    },
    "02_2": {
      "name": "02_2",
      "onend": "02_n",
      "vsrc": "02_2.mp4"
    },
    "02_3": {
      "name": "02_3",
      "onend": "02_n",
      "vsrc": "02_3.mp4"
    },
    "02_4": {
      "name": "02_4",
      "onend": "02_n",
      "vsrc": "02_4.mp4"
    },
    "02_5": {
      "name": "02_5",
      "onend": "02_n",
      "vsrc": "02_5.mp4"
    },
    "02_6": {
      "name": "02_6",
      "onend": "02_n",
      "vsrc": "02_6.mp4"
    },
    "02_7": {
      "name": "02_7",
      "onend": "02_n",
      "vsrc": "02_7.mp4"
    },
    "02_8": {
      "name": "02_8",
      "onend": {
        "scene": "02",
        "time": 16.3
      },
      "vsrc": "02_8.mp4"
    },
    "02_n": {
      "name": "02_n",
      "vsrc": "02_n.mp4",
      "events": [
        {
          "type": "click",
          "scene": "03",
          "constraints": {
            "timespan": [
              1
            ]
          }
        }
      ]
    },
    "03": {
      "name": "03",
      "vsrc": "03.mp4",
      "events": [
        {
          "type": "click",
          "scene": "03_1",
          "constraints": {
            "timespan": [
              16
            ],
            "hitbox": [
              9.8,
              48.21,
              22.15,
              13.69
            ]
          }
        },
        {
          "type": "click",
          "scene": "03_2",
          "constraints": {
            "timespan": [
              16
            ],
            "hitbox": [
              22.88,
              48.07,
              34.49,
              14.45
            ]
          }
        },
        {
          "type": "click",
          "scene": "03_3",
          "constraints": {
            "timespan": [
              16
            ],
            "hitbox": [
              35.35,
              48.21,
              46.84,
              14.52
            ]
          }
        },
        {
          "type": "click",
          "scene": "03_4",
          "constraints": {
            "timespan": [
              16
            ],
            "hitbox": [
              10.9,
              83.08,
              22.27,
              49.04
            ]
          }
        },
        {
          "type": "click",
          "scene": "03_5",
          "constraints": {
            "timespan": [
              16
            ],
            "hitbox": [
              23.13,
              82.73,
              34.74,
              49.04
            ]
          }
        },
        {
          "type": "click",
          "scene": "03_6",
          "constraints": {
            "timespan": [
              16
            ],
            "hitbox": [
              35.59,
              83.08,
              47.21,
              49.11
            ]
          }
        },
        {
          "type": "click",
          "scene": "03_7",
          "constraints": {
            "timespan": [
              16
            ],
            "hitbox": [
              48.31,
              83.14,
              59.31,
              15.96
            ]
          }
        },
        {
          "type": "click",
          "scene": "03_8",
          "constraints": {
            "timespan": [
              16
            ],
            "hitbox": [
              61.02,
              82.73,
              72.27,
              15.75
            ]
          }
        },
        {
          "type": "timeout",
          "span": 21000,
          "sound": {
            "src": [
              "delay/clip_01.mp3",
              "delay/clip_02.mp3",
              "delay/clip_03.mp3",
              "delay/clip_04.mp3",
              "delay/clip_05.mp3",
              "delay/clip_06.mp3",
              "delay/clip_07.mp3",
              "delay/clip_08.mp3",
              "delay/clip_09.mp3",
              "delay/clip_10.mp3",
              "delay/clip_11.mp3",
              "delay/clip_12.mp3",
              "delay/clip_13.mp3",
              "delay/clip_14.mp3",
              "delay/clip_15.mp3"
            ],
            "onend": {
              "type": "repeat",
              "unbound": true,
              "timeout": 4000
            }
          }
        },
        {
          "type": "timeout",
          "span": 4000,
          "single": true,
          "sound": {
            "src": "bg/03.mp3",
            "loop": true,
            "volume": 0.5
          },
          "scene_span": [
            "03",
            "03_1",
            "03_2",
            "03_3",
            "03_4",
            "03_5",
            "03_6",
            "03_7",
            "03_8"
          ]
        }
      ]
    },
    "03_1": {
      "name": "03_1",
      "onend": "03_n",
      "vsrc": "03_1.mp4"
    },
    "03_2": {
      "name": "03_2",
      "onend": "03_n",
      "vsrc": "03_2.mp4"
    },
    "03_3": {
      "name": "03_3",
      "onend": "03_n",
      "vsrc": "03_3.mp4"
    },
    "03_4": {
      "name": "03_4",
      "onend": "03_n",
      "vsrc": "03_4.mp4"
    },
    "03_5": {
      "name": "03_5",
      "onend": "03_n",
      "vsrc": "03_5.mp4"
    },
    "03_6": {
      "name": "03_6",
      "onend": "03_n",
      "vsrc": "03_6.mp4"
    },
    "03_7": {
      "name": "03_7",
      "onend": "03_n",
      "vsrc": "03_7.mp4"
    },
    "03_8": {
      "name": "03_8",
      "onend": {
        "scene": "03",
        "time": 16.3
      },
      "vsrc": "03_8.mp4"
    },
    "03_n": {
      "name": "03_n",
      "vsrc": "03_n.mp4",
      "events": [
        {
          "type": "click",
          "scene": "04",
          "constraints": {
            "timespan": [
              1.3
            ]
          }
        }
      ]
    },
    "04": {
      "name": "04",
      "vsrc": "04.mp4",
      "events": [
        {
          "type": "click",
          "scene": "04_1",
          "constraints": {
            "timespan": [
              20.5
            ],
            "hitbox": [
              9.8,
              48.07,
              20.93,
              14.24
            ]
          }
        },
        {
          "type": "click",
          "scene": "04_2",
          "constraints": {
            "timespan": [
              20.5
            ],
            "hitbox": [
              22.27,
              48.21,
              33.88,
              14.31
            ]
          }
        },
        {
          "type": "click",
          "scene": "04_3",
          "constraints": {
            "timespan": [
              20.5
            ],
            "hitbox": [
              34.74,
              48.21,
              46.84,
              14.72
            ]
          }
        },
        {
          "type": "click",
          "scene": "04_4",
          "constraints": {
            "timespan": [
              20.5
            ],
            "hitbox": [
              10.78,
              83.56,
              22.39,
              49.59
            ]
          }
        },
        {
          "type": "click",
          "scene": "04_5",
          "constraints": {
            "timespan": [
              20.5
            ],
            "hitbox": [
              23.61,
              83.08,
              34.98,
              49.38
            ]
          }
        },
        {
          "type": "click",
          "scene": "04_6",
          "constraints": {
            "timespan": [
              20.5
            ],
            "hitbox": [
              36.08,
              82.8,
              47.7,
              49.38
            ]
          }
        },
        {
          "type": "click",
          "scene": "04_7",
          "constraints": {
            "timespan": [
              20.5
            ],
            "hitbox": [
              49.41,
              82.73,
              59.68,
              16.44
            ]
          }
        },
        {
          "type": "click",
          "scene": "04_8",
          "constraints": {
            "timespan": [
              20.5
            ],
            "hitbox": [
              61.76,
              82.18,
              73.86,
              15.89
            ]
          }
        },
        {
          "type": "timeout",
          "span": 25000,
          "scene_span": "04",
          "sound": {
            "src": [
              "delay/clip_01.mp3",
              "delay/clip_02.mp3",
              "delay/clip_03.mp3",
              "delay/clip_04.mp3",
              "delay/clip_05.mp3",
              "delay/clip_06.mp3",
              "delay/clip_07.mp3",
              "delay/clip_08.mp3",
              "delay/clip_09.mp3",
              "delay/clip_10.mp3",
              "delay/clip_11.mp3",
              "delay/clip_12.mp3",
              "delay/clip_13.mp3",
              "delay/clip_14.mp3",
              "delay/clip_15.mp3"
            ],
            "onend": {
              "type": "repeat",
              "unbound": true,
              "timeout": 4000
            }
          }
        },
        {
          "type": "timeout",
          "span": 7000,
          "sound": {
            "src": "bg/04.mp3",
            "loop": true,
            "volume": 0.5
          },
          "scene_span": [
            "04",
            "04_1",
            "04_2",
            "04_3",
            "04_4",
            "04_5",
            "04_6",
            "04_7",
            "04_8"
          ]
        }
      ]
    },
    "04_1": {
      "name": "04_1",
      "onend": "04_n",
      "vsrc": "04_1.mp4"
    },
    "04_2": {
      "name": "04_2",
      "onend": "04_n",
      "vsrc": "04_2.mp4"
    },
    "04_3": {
      "name": "04_3",
      "onend": "04_n",
      "vsrc": "04_3.mp4"
    },
    "04_4": {
      "name": "04_4",
      "onend": "04_n",
      "vsrc": "04_4.mp4"
    },
    "04_5": {
      "name": "04_5",
      "onend": "04_n",
      "vsrc": "04_5.mp4"
    },
    "04_6": {
      "name": "04_6",
      "onend": "04_n",
      "vsrc": "04_6.mp4"
    },
    "04_7": {
      "name": "04_7",
      "onend": "04_n",
      "vsrc": "04_7.mp4"
    },
    "04_8": {
      "name": "04_8",
      "onend": {
        "scene": "04",
        "time": 20.9
      },
      "vsrc": "04_8.mp4"
    },
    "04_n": {
      "name": "04_n",
      "vsrc": "04_n.mp4",
      "events": [
        {
          "type": "click",
          "scene": "05",
          "constraints": {
            "timespan": [
              2.6
            ]
          }
        }
      ]
    },
    "05": {
      "name": "05",
      "vsrc": "05.mp4",
      "events": [
        {
          "type": "click",
          "scene": "05_1",
          "constraints": {
            "timespan": [
              21.5
            ],
            "hitbox": [
              8.94,
              48.14,
              21.29,
              13.69
            ]
          }
        },
        {
          "type": "click",
          "scene": "05_1",
          "constraints": {
            "timespan": [
              21.5
            ],
            "hitbox": [
              21.9,
              48.42,
              33.64,
              14.04
            ]
          }
        },
        {
          "type": "click",
          "scene": "05_1",
          "constraints": {
            "timespan": [
              21.5
            ],
            "hitbox": [
              35.23,
              48.49,
              46.23,
              14.93
            ]
          }
        },
        {
          "type": "click",
          "scene": "05_1",
          "constraints": {
            "timespan": [
              21.5
            ],
            "hitbox": [
              10.04,
              83.14,
              21.66,
              49.17
            ]
          }
        },
        {
          "type": "click",
          "scene": "05_1",
          "constraints": {
            "timespan": [
              21.5
            ],
            "hitbox": [
              22.39,
              83.01,
              33.76,
              49.04
            ]
          }
        },
        {
          "type": "click",
          "scene": "05_1",
          "constraints": {
            "timespan": [
              21.5
            ],
            "hitbox": [
              34.74,
              83.28,
              46.72,
              49.45
            ]
          }
        },
        {
          "type": "click",
          "scene": "05_1",
          "constraints": {
            "timespan": [
              21.5
            ],
            "hitbox": [
              47.7,
              82.66,
              58.94,
              15.75
            ]
          }
        },
        {
          "type": "click",
          "scene": "05_1",
          "constraints": {
            "timespan": [
              21.5
            ],
            "hitbox": [
              59.92,
              82.8,
              72.76,
              16.31
            ]
          }
        },
        {
          "type": "timeout",
          "span": 26000,
          "sound": {
            "src": [
              "delay/clip_01.mp3",
              "delay/clip_02.mp3",
              "delay/clip_03.mp3",
              "delay/clip_04.mp3",
              "delay/clip_05.mp3",
              "delay/clip_06.mp3",
              "delay/clip_07.mp3",
              "delay/clip_08.mp3",
              "delay/clip_09.mp3",
              "delay/clip_10.mp3",
              "delay/clip_11.mp3",
              "delay/clip_12.mp3",
              "delay/clip_13.mp3",
              "delay/clip_14.mp3",
              "delay/clip_15.mp3"
            ],
            "onend": {
              "type": "repeat",
              "unbound": true,
              "timeout": 4000
            }
          }
        },
        {
          "type": "timeout",
          "span": 6000,
          "single": true,
          "sound": {
            "src": "bg/05.mp3",
            "loop": true,
            "volume": 0.5
          },
          "scene_span": [
            "05",
            "05_1",
            "05_2",
            "05_3",
            "05_4",
            "05_5",
            "05_6",
            "05_7",
            "05_8"
          ]
        }
      ]
    },
    "05_1": {
      "name": "05_1",
      "onend": "break",
      "vsrc": "05_1.mp4"
    },
    "05_2": {
      "name": "05_2",
      "onend": "break",
      "vsrc": "05_2.mp4"
    },
    "05_3": {
      "name": "05_3",
      "onend": "break",
      "vsrc": "05_3.mp4"
    },
    "05_4": {
      "name": "05_4",
      "onend": "break",
      "vsrc": "05_4.mp4"
    },
    "05_5": {
      "name": "05_5",
      "onend": "break",
      "vsrc": "05_5.mp4"
    },
    "05_6": {
      "name": "05_6",
      "onend": "break",
      "vsrc": "05_6.mp4"
    },
    "05_7": {
      "name": "05_7",
      "onend": "break",
      "vsrc": "05_7.mp4"
    },
    "05_8": {
      "name": "05_8",
      "onend": {
        "scene": "05",
        "time": 21.8
      },
      "vsrc": "05_8.mp4"
    },
    "05_n": {
      "name": "05_n",
      "vsrc": "05_n.mp4",
      "events": [
        {
          "type": "click",
          "scene": "06",
          "constraints": {
            "timespan": [
              2.8
            ]
          }
        }
      ]
    },
    "06": {
      "name": "06",
      "vsrc": "06.mp4",
      "events": [
        {
          "type": "click",
          "scene": "06_1",
          "constraints": {
            "timespan": [
              27
            ],
            "hitbox": [
              11.63,
              47.66,
              23.49,
              13.69
            ]
          }
        },
        {
          "type": "click",
          "scene": "06_2",
          "constraints": {
            "timespan": [
              27
            ],
            "hitbox": [
              24.1,
              48.28,
              35.84,
              14.1
            ]
          }
        },
        {
          "type": "click",
          "scene": "06_3",
          "constraints": {
            "timespan": [
              27
            ],
            "hitbox": [
              36.82,
              48.21,
              47.94,
              14.65
            ]
          }
        },
        {
          "type": "click",
          "scene": "06_4",
          "constraints": {
            "timespan": [
              27
            ],
            "hitbox": [
              11.27,
              82.32,
              21.66,
              48.21
            ]
          }
        },
        {
          "type": "click",
          "scene": "06_5",
          "constraints": {
            "timespan": [
              27
            ],
            "hitbox": [
              24.47,
              82.39,
              34.74,
              48.76
            ]
          }
        },
        {
          "type": "click",
          "scene": "06_6",
          "constraints": {
            "timespan": [
              27
            ],
            "hitbox": [
              35.72,
              82.73,
              47.58,
              48.76
            ]
          }
        },
        {
          "type": "click",
          "scene": "06_7",
          "constraints": {
            "timespan": [
              27
            ],
            "hitbox": [
              49.41,
              82.53,
              60.29,
              15.27
            ]
          }
        },
        {
          "type": "click",
          "scene": "06_8",
          "constraints": {
            "timespan": [
              27
            ],
            "hitbox": [
              62.73,
              82.87,
              73,
              15.82
            ]
          }
        },
        {
          "type": "timeout",
          "span": 32000,
          "sound": {
            "src": [
              "delay/clip_01.mp3",
              "delay/clip_02.mp3",
              "delay/clip_03.mp3",
              "delay/clip_04.mp3",
              "delay/clip_05.mp3",
              "delay/clip_06.mp3",
              "delay/clip_07.mp3",
              "delay/clip_08.mp3",
              "delay/clip_09.mp3",
              "delay/clip_10.mp3",
              "delay/clip_11.mp3",
              "delay/clip_12.mp3",
              "delay/clip_13.mp3",
              "delay/clip_14.mp3",
              "delay/clip_15.mp3"
            ],
            "onend": {
              "type": "repeat",
              "unbound": true,
              "timeout": 4000
            }
          }
        },
        {
          "type": "timeout",
          "span": 5000,
          "single": true,
          "sound": {
            "src": "bg/06.mp3",
            "loop": true,
            "volume": 0.5
          },
          "scene_span": [
            "06",
            "06_1",
            "06_2",
            "06_3",
            "06_4",
            "06_5",
            "06_6",
            "06_7",
            "06_8"
          ]
        }
      ]
    },
    "06_1": {
      "name": "06_1",
      "onend": "06_n",
      "vsrc": "06_1.mp4"
    },
    "06_2": {
      "name": "06_2",
      "onend": "06_n",
      "vsrc": "06_2.mp4"
    },
    "06_3": {
      "name": "06_3",
      "onend": "06_n",
      "vsrc": "06_3.mp4"
    },
    "06_4": {
      "name": "06_4",
      "onend": "06_n",
      "vsrc": "06_4.mp4"
    },
    "06_5": {
      "name": "06_5",
      "onend": "06_n",
      "vsrc": "06_5.mp4"
    },
    "06_6": {
      "name": "06_6",
      "onend": "06_n",
      "vsrc": "06_6.mp4"
    },
    "06_7": {
      "name": "06_7",
      "onend": "06_n",
      "vsrc": "06_7.mp4"
    },
    "06_8": {
      "name": "06_8",
      "onend": {
        "scene": "06",
        "time": 27.4
      },
      "vsrc": "06_8.mp4"
    },
    "06_n": {
      "name": "06_n",
      "vsrc": "06_n.mp4",
      "events": [
        {
          "type": "click",
          "scene": "07",
          "constraints": {
            "timespan": [
              2.5
            ]
          }
        }
      ]
    },
    "07": {
      "name": "07",
      "vsrc": "07.mp4",
      "events": [
        {
          "type": "click",
          "scene": "07_1",
          "constraints": {
            "timespan": [
              27
            ],
            "hitbox": [
              10.53,
              48.21,
              22.64,
              14.04
            ]
          }
        },
        {
          "type": "click",
          "scene": "07_2",
          "constraints": {
            "timespan": [
              27
            ],
            "hitbox": [
              23.74,
              47.94,
              34.13,
              14.38
            ]
          }
        },
        {
          "type": "click",
          "scene": "07_3",
          "constraints": {
            "timespan": [
              27
            ],
            "hitbox": [
              35.72,
              48.01,
              46.96,
              14.72
            ]
          }
        },
        {
          "type": "click",
          "scene": "07_4",
          "constraints": {
            "timespan": [
              27
            ],
            "hitbox": [
              11.02,
              83.56,
              22.51,
              49.45
            ]
          }
        },
        {
          "type": "click",
          "scene": "07_5",
          "constraints": {
            "timespan": [
              27
            ],
            "hitbox": [
              23.86,
              83.56,
              34.74,
              49.52
            ]
          }
        },
        {
          "type": "click",
          "scene": "07_6",
          "constraints": {
            "timespan": [
              27
            ],
            "hitbox": [
              36.21,
              83.35,
              47.09,
              49.66
            ]
          }
        },
        {
          "type": "click",
          "scene": "07_7",
          "constraints": {
            "timespan": [
              27
            ],
            "hitbox": [
              48.55,
              83.14,
              60.29,
              16.17
            ]
          }
        },
        {
          "type": "click",
          "scene": "07_8",
          "constraints": {
            "timespan": [
              27
            ],
            "hitbox": [
              61.63,
              82.8,
              73.37,
              16.24
            ]
          }
        },
        {
          "type": "timeout",
          "span": 32000,
          "sound": {
            "src": [
              "delay/clip_01.mp3",
              "delay/clip_02.mp3",
              "delay/clip_03.mp3",
              "delay/clip_04.mp3",
              "delay/clip_05.mp3",
              "delay/clip_06.mp3",
              "delay/clip_07.mp3",
              "delay/clip_08.mp3",
              "delay/clip_09.mp3",
              "delay/clip_10.mp3",
              "delay/clip_11.mp3",
              "delay/clip_12.mp3",
              "delay/clip_13.mp3",
              "delay/clip_14.mp3",
              "delay/clip_15.mp3"
            ],
            "onend": {
              "type": "repeat",
              "unbound": true,
              "timeout": 4000
            }
          }
        },
        {
          "type": "timeout",
          "span": 5000,
          "single": true,
          "sound": {
            "src": "bg/07.mp3",
            "loop": true,
            "volume": 0.5
          },
          "scene_span": [
            "07",
            "07_1",
            "07_2",
            "07_3",
            "07_4",
            "07_5",
            "07_6",
            "07_7",
            "07_8"
          ]
        }
      ]
    },
    "07_1": {
      "name": "07_1",
      "onend": "interruption",
      "vsrc": "07_1.mp4"
    },
    "07_2": {
      "name": "07_2",
      "onend": "interruption",
      "vsrc": "07_2.mp4"
    },
    "07_3": {
      "name": "07_3",
      "onend": "interruption",
      "vsrc": "07_3.mp4"
    },
    "07_4": {
      "name": "07_4",
      "onend": "interruption",
      "vsrc": "07_4.mp4"
    },
    "07_5": {
      "name": "07_5",
      "onend": "interruption",
      "vsrc": "07_5.mp4"
    },
    "07_6": {
      "name": "07_6",
      "onend": "interruption",
      "vsrc": "07_6.mp4"
    },
    "07_7": {
      "name": "07_7",
      "onend": "interruption",
      "vsrc": "07_7.mp4"
    },
    "07_8": {
      "name": "07_8",
      "onend": {
        "scene": "07",
        "time": 27.6
      },
      "vsrc": "07_8.mp4"
    },
    "07_n": {
      "name": "07_n",
      "vsrc": "07_n.mp4",
      "events": [
        {
          "type": "click",
          "scene": "08",
          "constraints": {
            "timespan": [
              1.1
            ]
          }
        }
      ]
    },
    "08": {
      "name": "08",
      "vsrc": "08.mp4",
      "events": [
        {
          "type": "click",
          "scene": "08_1",
          "constraints": {
            "timespan": [
              21
            ],
            "hitbox": [
              10.66,
              47.94,
              22.51,
              13.69
            ]
          }
        },
        {
          "type": "click",
          "scene": "08_2",
          "constraints": {
            "timespan": [
              21
            ],
            "hitbox": [
              23.37,
              48.14,
              34.86,
              14.1
            ]
          }
        },
        {
          "type": "click",
          "scene": "08_3",
          "constraints": {
            "timespan": [
              21
            ],
            "hitbox": [
              35.96,
              48.21,
              47.09,
              14.59
            ]
          }
        },
        {
          "type": "click",
          "scene": "08_4",
          "constraints": {
            "timespan": [
              21
            ],
            "hitbox": [
              9.92,
              82.73,
              21.54,
              48.42
            ]
          }
        },
        {
          "type": "click",
          "scene": "08_5",
          "constraints": {
            "timespan": [
              21
            ],
            "hitbox": [
              22.88,
              82.94,
              34.37,
              48.76
            ]
          }
        },
        {
          "type": "click",
          "scene": "08_6",
          "constraints": {
            "timespan": [
              21
            ],
            "hitbox": [
              35.96,
              82.53,
              46.84,
              48.9
            ]
          }
        },
        {
          "type": "click",
          "scene": "08_7",
          "constraints": {
            "timespan": [
              21
            ],
            "hitbox": [
              49.04,
              82.25,
              59.68,
              15.34
            ]
          }
        },
        {
          "type": "click",
          "scene": "08_8",
          "constraints": {
            "timespan": [
              21
            ],
            "hitbox": [
              62,
              82.25,
              73,
              15.48
            ]
          }
        },
        {
          "type": "timeout",
          "span": 26000,
          "sound": {
            "src": [
              "delay/clip_01.mp3",
              "delay/clip_02.mp3",
              "delay/clip_03.mp3",
              "delay/clip_04.mp3",
              "delay/clip_05.mp3",
              "delay/clip_06.mp3",
              "delay/clip_07.mp3",
              "delay/clip_08.mp3",
              "delay/clip_09.mp3",
              "delay/clip_10.mp3",
              "delay/clip_11.mp3",
              "delay/clip_12.mp3",
              "delay/clip_13.mp3",
              "delay/clip_14.mp3",
              "delay/clip_15.mp3"
            ],
            "onend": {
              "type": "repeat",
              "unbound": true,
              "timeout": 4000
            }
          }
        },
        {
          "type": "timeout",
          "span": 4000,
          "single": true,
          "sound": {
            "src": "bg/08.mp3",
            "loop": true,
            "volume": 0.5
          },
          "scene_span": [
            "08",
            "08_1",
            "08_2",
            "08_3",
            "08_4",
            "08_5",
            "08_6",
            "08_7",
            "08_8"
          ]
        }
      ]
    },
    "08_1": {
      "name": "08_1",
      "onend": "08_n",
      "vsrc": "08_1.mp4"
    },
    "08_2": {
      "name": "08_2",
      "onend": "08_n",
      "vsrc": "08_2.mp4"
    },
    "08_3": {
      "name": "08_3",
      "onend": "08_n",
      "vsrc": "08_3.mp4"
    },
    "08_4": {
      "name": "08_4",
      "onend": "08_n",
      "vsrc": "08_4.mp4"
    },
    "08_5": {
      "name": "08_5",
      "onend": "08_n",
      "vsrc": "08_5.mp4"
    },
    "08_6": {
      "name": "08_6",
      "onend": "08_n",
      "vsrc": "08_6.mp4"
    },
    "08_7": {
      "name": "08_7",
      "onend": "08_n",
      "vsrc": "08_7.mp4"
    },
    "08_8": {
      "name": "08_8",
      "onend": {
        "scene": "08",
        "time": 21.6
      },
      "vsrc": "08_8.mp4"
    },
    "08_n": {
      "name": "08_n",
      "vsrc": "08_n.mp4",
      "events": [
        {
          "type": "click",
          "scene": "09",
          "constraints": {
            "timespan": [
              1.2
            ]
          }
        }
      ]
    },
    "09": {
      "name": "09",
      "vsrc": "09.mp4",
      "events": [
        {
          "type": "click",
          "scene": "09_1",
          "constraints": {
            "timespan": [
              23
            ],
            "hitbox": [
              12.25,
              48.62,
              24.35,
              14.24
            ]
          }
        },
        {
          "type": "click",
          "scene": "09_2",
          "constraints": {
            "timespan": [
              23
            ],
            "hitbox": [
              25.69,
              48.76,
              37.18,
              14.65
            ]
          }
        },
        {
          "type": "click",
          "scene": "09_3",
          "constraints": {
            "timespan": [
              23
            ],
            "hitbox": [
              38.65,
              48.69,
              50.02,
              15.07
            ]
          }
        },
        {
          "type": "click",
          "scene": "09_4",
          "constraints": {
            "timespan": [
              23
            ],
            "hitbox": [
              11.76,
              84.59,
              22.51,
              50.34
            ]
          }
        },
        {
          "type": "click",
          "scene": "09_5",
          "constraints": {
            "timespan": [
              23
            ],
            "hitbox": [
              25.33,
              84.31,
              36.45,
              50.48
            ]
          }
        },
        {
          "type": "click",
          "scene": "09_6",
          "constraints": {
            "timespan": [
              23
            ],
            "hitbox": [
              38.16,
              84.18,
              49.41,
              50.55
            ]
          }
        },
        {
          "type": "click",
          "scene": "09_7",
          "constraints": {
            "timespan": [
              23
            ],
            "hitbox": [
              51.49,
              82.8,
              61.76,
              15.82
            ]
          }
        },
        {
          "type": "click",
          "scene": "09_8",
          "constraints": {
            "timespan": [
              23
            ],
            "hitbox": [
              64.69,
              82.94,
              75.45,
              16.1
            ]
          }
        },
        {
          "type": "timeout",
          "span": 28000,
          "sound": {
            "src": [
              "delay/clip_01.mp3",
              "delay/clip_02.mp3",
              "delay/clip_03.mp3",
              "delay/clip_04.mp3",
              "delay/clip_05.mp3",
              "delay/clip_06.mp3",
              "delay/clip_07.mp3",
              "delay/clip_08.mp3",
              "delay/clip_09.mp3",
              "delay/clip_10.mp3",
              "delay/clip_11.mp3",
              "delay/clip_12.mp3",
              "delay/clip_13.mp3",
              "delay/clip_14.mp3",
              "delay/clip_15.mp3"
            ],
            "onend": {
              "type": "repeat",
              "unbound": true,
              "timeout": 4000
            }
          }
        },
        {
          "type": "timeout",
          "span": 6000,
          "single": true,
          "sound": {
            "src": "bg/09.mp3",
            "loop": true,
            "volume": 0.5
          },
          "scene_span": [
            "09",
            "09_1",
            "09_2",
            "09_3",
            "09_4",
            "09_5",
            "09_6",
            "09_7",
            "09_8"
          ]
        }
      ]
    },
    "09_1": {
      "name": "09_1",
      "onend": "09_n",
      "vsrc": "09_1.mp4"
    },
    "09_2": {
      "name": "09_2",
      "onend": "09_n",
      "vsrc": "09_2.mp4"
    },
    "09_3": {
      "name": "09_3",
      "onend": "09_n",
      "vsrc": "09_3.mp4"
    },
    "09_4": {
      "name": "09_4",
      "onend": "09_n",
      "vsrc": "09_4.mp4"
    },
    "09_5": {
      "name": "09_5",
      "onend": "09_n",
      "vsrc": "09_5.mp4"
    },
    "09_6": {
      "name": "09_6",
      "onend": "09_n",
      "vsrc": "09_6.mp4"
    },
    "09_7": {
      "name": "09_7",
      "onend": "09_n",
      "vsrc": "09_7.mp4"
    },
    "09_8": {
      "name": "09_8",
      "onend": {
        "scene": "09",
        "time": 23.5
      },
      "vsrc": "09_8.mp4"
    },
    "09_n": {
      "name": "09_n",
      "vsrc": "09_n.mp4",
      "events": [
        {
          "type": "click",
          "scene": "02",
          "constraints": {
            "timespan": [
              0.6
            ]
          }
        }
      ]
    },
    "10": {
      "name": "10",
      "vsrc": "10.mp4",
      "events": [
        {
          "type": "click",
          "scene": "10_1",
          "constraints": {
            "timespan": [
              17
            ],
            "hitbox": [
              12.73,
              48.42,
              23.61,
              14.24
            ]
          }
        },
        {
          "type": "click",
          "scene": "10_2",
          "constraints": {
            "timespan": [
              17
            ],
            "hitbox": [
              24.96,
              48.62,
              36.08,
              14.86
            ]
          }
        },
        {
          "type": "click",
          "scene": "10_3",
          "constraints": {
            "timespan": [
              17
            ],
            "hitbox": [
              37.92,
              48.69,
              49.53,
              15.62
            ]
          }
        },
        {
          "type": "click",
          "scene": "10_4",
          "constraints": {
            "timespan": [
              17
            ],
            "hitbox": [
              12.12,
              83.49,
              22.88,
              49.52
            ]
          }
        },
        {
          "type": "click",
          "scene": "10_5",
          "constraints": {
            "timespan": [
              17
            ],
            "hitbox": [
              24.84,
              83.56,
              35.72,
              49.59
            ]
          }
        },
        {
          "type": "click",
          "scene": "10_6",
          "constraints": {
            "timespan": [
              17
            ],
            "hitbox": [
              37.92,
              83.63,
              49.04,
              49.52
            ]
          }
        },
        {
          "type": "click",
          "scene": "10_7",
          "constraints": {
            "timespan": [
              17
            ],
            "hitbox": [
              50.63,
              82.94,
              62.61,
              15.96
            ]
          }
        },
        {
          "type": "click",
          "scene": "10_8",
          "constraints": {
            "timespan": [
              17
            ],
            "hitbox": [
              64.32,
              82.73,
              75.81,
              15.75
            ]
          }
        },
        {
          "type": "timeout",
          "span": 22000,
          "sound": {
            "src": [
              "delay/clip_01.mp3",
              "delay/clip_02.mp3",
              "delay/clip_03.mp3",
              "delay/clip_04.mp3",
              "delay/clip_05.mp3",
              "delay/clip_06.mp3",
              "delay/clip_07.mp3",
              "delay/clip_08.mp3",
              "delay/clip_09.mp3",
              "delay/clip_10.mp3",
              "delay/clip_11.mp3",
              "delay/clip_12.mp3",
              "delay/clip_13.mp3",
              "delay/clip_14.mp3",
              "delay/clip_15.mp3"
            ],
            "onend": {
              "type": "repeat",
              "unbound": true,
              "timeout": 4000
            }
          }
        },
        {
          "type": "timeout",
          "span": 5000,
          "single": true,
          "sound": {
            "src": "bg/10.mp3",
            "loop": true,
            "volume": 0.5
          },
          "scene_span": [
            "10",
            "10_1",
            "10_2",
            "10_3",
            "10_4",
            "10_5",
            "10_6",
            "10_7",
            "10_8"
          ]
        }
      ]
    },
    "10_1": {
      "name": "10_1",
      "onend": "fin_01",
      "vsrc": "10_1.mp4"
    },
    "10_2": {
      "name": "10_2",
      "onend": "fin_01",
      "vsrc": "10_2.mp4"
    },
    "10_3": {
      "name": "10_3",
      "onend": "fin_01",
      "vsrc": "10_3.mp4"
    },
    "10_4": {
      "name": "10_4",
      "onend": "fin_01",
      "vsrc": "10_4.mp4"
    },
    "10_5": {
      "name": "10_5",
      "onend": "fin_01",
      "vsrc": "10_5.mp4"
    },
    "10_6": {
      "name": "10_6",
      "onend": "fin_01",
      "vsrc": "10_6.mp4"
    },
    "10_7": {
      "name": "10_7",
      "onend": "finale",
      "vsrc": "10_7.mp4"
    },
    "10_8": {
      "name": "10_8",
      "onend": {
        "scene": "10",
        "time": 17.1
      },
      "vsrc": "10_8.mp4"
    },
    "break": {
      "name": "break",
      "onend": "05_n",
      "vsrc": "break.mp4"
    },
    "fin_01": {
      "name": "fin_01",
      "onend": "fin_02",
      "vsrc": "fin_01.mp4"
    },
    "fin_02": {
      "name": "fin_02",
      "onend": "fin_03",
      "vsrc": "fin_02.mp4"
    },
    "fin_03": {
      "name": "fin_03",
      "onend": "00_1",
      "vsrc": "fin_03.mp4"
    },
    "interruption": {
      "name": "interuption",
      "vsrc": "interuption.mp4",
      "events": [
        {
          "type": "click",
          "scene": "interuption_1",
          "constraints": {
            "timespan": [
              31.5
            ],
            "hitbox": [
              6.13,
              43.33,
              17.99,
              9.5
            ]
          }
        },
        {
          "type": "click",
          "scene": "interuption_2",
          "constraints": {
            "timespan": [
              31.5
            ],
            "hitbox": [
              6.13,
              92.91,
              17.99,
              58.66
            ]
          }
        },
        {
          "type": "click",
          "scene": "interuption_3",
          "constraints": {
            "timespan": [
              31.5
            ],
            "hitbox": [
              19.7,
              43.12,
              31.56,
              9.5
            ]
          }
        },
        {
          "type": "click",
          "scene": "interuption_4",
          "constraints": {
            "timespan": [
              31.5
            ],
            "hitbox": [
              19.58,
              92.63,
              32.42,
              58.53
            ]
          }
        },
        {
          "type": "click",
          "scene": "interuption_5",
          "constraints": {
            "timespan": [
              31.5
            ],
            "hitbox": [
              34.86,
              83.01,
              45.99,
              16.03
            ]
          }
        },
        {
          "type": "click",
          "scene": "interuption_6",
          "constraints": {
            "timespan": [
              31.5
            ],
            "hitbox": [
              48.31,
              45.46,
              59.8,
              7.09
            ]
          }
        },
        {
          "type": "click",
          "scene": "interuption_7",
          "constraints": {
            "timespan": [
              31.5
            ],
            "hitbox": [
              48.92,
              92.43,
              60.29,
              58.73
            ]
          }
        },
        {
          "type": "click",
          "scene": "interuption_8",
          "constraints": {
            "timespan": [
              31.5
            ],
            "hitbox": [
              62.37,
              83.76,
              85.23,
              16.58
            ]
          }
        },
        {
          "type": "click",
          "scene": "interuption_9",
          "constraints": {
            "timespan": [
              31.5
            ],
            "hitbox": [
              87.31,
              82.39,
              99.04,
              15.48
            ]
          }
        }
      ]
    },
    "interruption_1": {
      "name": "interruption_1",
      "onend": "07_n",
      "vsrc": "interruption_1.mp4"
    },
    "interruption_2": {
      "name": "interruption_2",
      "onend": "07_n",
      "vsrc": "interruption_2.mp4"
    },
    "interruption_3": {
      "name": "interruption_3",
      "onend": "07_n",
      "vsrc": "interruption_3.mp4"
    },
    "interruption_4": {
      "name": "interruption_4",
      "onend": "07_n",
      "vsrc": "interruption_4.mp4"
    },
    "interruption_5": {
      "name": "interruption_5",
      "onend": "07_n",
      "vsrc": "interruption_5.mp4"
    },
    "interruption_6": {
      "name": "interruption_6",
      "onend": "07_n",
      "vsrc": "interruption_6.mp4"
    },
    "interruption_7": {
      "name": "interruption_7",
      "onend": "07_n",
      "vsrc": "interruption_7.mp4"
    },
    "interruption_8": {
      "name": "interruption_8",
      "onend": "07_n",
      "vsrc": "interruption_8.mp4"
    },
    "interruption_9": {
      "name": "interruption_9",
      "onend": "07_n",
      "vsrc": "interruption_9.mp4"
    }
  }
}
